anarpy/__init__.py
anarpy/models/__init__.py
anarpy/models/HuberBraun/__init__.py
anarpy/models/HuberBraun/netwHBIh2.py
anarpy/models/WilsonCowan/__init__.py
anarpy/models/WilsonCowan/netwWilsonCowan.py
anarpy/models/WilsonCowan/netwWilsonCowanFull.py
anarpy/models/WilsonCowan/netwWilsonCowanPlastic.py
anarpy/models/others/__init__.py
anarpy/models/others/netEIF_EImix.py
anarpy/utils/__init__.py
anarpy-0.1.8.dist-info/LICENSE
anarpy-0.1.8.dist-info/METADATA
anarpy-0.1.8.dist-info/WHEEL
anarpy-0.1.8.dist-info/top_level.txt
anarpy-0.1.8.dist-info/RECORD
