Metadata-Version: 2.1
Name: anarpy
Version: 0.1.8
Summary: Analysis and Replication in Python
Home-page: https://anarpy.readthedocs.io
Author: Valparaiso Neural Dynamics Laboratory
Author-email: javier.palma@cinv.cl
License: UNKNOWN
Project-URL: Bug Tracker, https://github.com/vandal-uv/anarpy/issues
Platform: UNKNOWN
Classifier: Programming Language :: Python :: 3
Classifier: License :: OSI Approved :: MIT License
Classifier: Operating System :: OS Independent
Requires-Python: >=3.6
License-File: LICENSE
